{
  "startedAt": "2026-03-05T18:17:43.239Z",
  "url": "https://x.com/screenhand_/status/2029620157203763699",
  "editText": "ScreenHand helps AI agents automate real Mac workflows end-to-end with OCR, native app control, and Chrome automation via MCP. Explore: https://screenhand.com #AIAgents #MCP #macOS #Automation",
  "steps": [
    {
      "step": "focus",
      "result": {
        "ok": true,
        "text": "Focused com.google.Chrome",
        "raw": {
          "_meta": {
            "memoryHints": [
              "💡 Memory: This matches strategy \"Save current document\" (10 wins, 0 fails). Next step: key({\"combo\":\"cmd+s\"})"
            ]
          },
          "content": [
            {
              "type": "text",
              "text": "Focused com.google.Chrome"
            }
          ]
        }
      }
    },
    {
      "step": "tabs",
      "result": {
        "ok": true,
        "text": "[2D89E7C0C6D271EC223D4023594A88FD] ScreenHand on X: &quot;ScreenHand helps AI agents automate real Mac workflows: OCR vision, native app control, Chrome automation, and AppleScript via MCP. Try it: https://t.co/mLvfJJOWjq #AIAgents #MCP #macOS&quot; / X — https://x.com/screenhand_/status/2029620157203763699\n[07540E6945A5598C6E565A46DEACE8B4] Inbox - singhaldeoli114@gmail.com - Gmail — https://mail.google.com/mail/u/0/#inbox\n[50A0E3A47A679D689B43FDB9E35FF819] Instagram — https://www.instagram.com/",
        "raw": {
          "_meta": {
            "memoryHints": [
              "💡 Memory: This matches strategy \"focus → browser_tabs → browser_navigate → windows → screenshot_file → click_text → type_text → key (com.google.Chrome, https://x.com/compose/post, What’s happening?)\" (11 wins, 0 fails). Next step: browser_navigate({\"url\":\"https://x.com/compose/post\",\"tabId\":\"2D89E7C0C6D271EC223D4023594A88FD\"})"
            ]
          },
          "content": [
            {
              "type": "text",
              "text": "[2D89E7C0C6D271EC223D4023594A88FD] ScreenHand on X: &quot;ScreenHand helps AI agents automate real Mac workflows: OCR vision, native app control, Chrome automation, and AppleScript via MCP. Try it: https://t.co/mLvfJJOWjq #AIAgents #MCP #macOS&quot; / X — https://x.com/screenhand_/status/2029620157203763699\n[07540E6945A5598C6E565A46DEACE8B4] Inbox - singhaldeoli114@gmail.com - Gmail — https://mail.google.com/mail/u/0/#inbox\n[50A0E3A47A679D689B43FDB9E35FF819] Instagram — https://www.instagram.com/"
            }
          ]
        }
      }
    },
    {
      "step": "navigate",
      "result": {
        "ok": true,
        "text": "Navigated to: X",
        "raw": {
          "_meta": {
            "memoryHints": [
              "💡 Memory: This matches strategy \"focus → browser_tabs → browser_navigate → windows → screenshot_file → click_text → type_text → key (com.google.Chrome, https://x.com/compose/post, What’s happening?)\" (11 wins, 0 fails). Next step: windows"
            ]
          },
          "content": [
            {
              "type": "text",
              "text": "Navigated to: X"
            }
          ]
        }
      }
    },
    {
      "step": "wait",
      "result": {
        "ok": true,
        "text": "Condition met",
        "raw": {
          "content": [
            {
              "type": "text",
              "text": "Condition met"
            }
          ]
        }
      }
    },
    {
      "step": "openMenu",
      "result": {
        "ok": true,
        "text": "{\n  \"ok\": true\n}",
        "raw": {
          "content": [
            {
              "type": "text",
              "text": "{\n  \"ok\": true\n}"
            }
          ]
        }
      }
    },
    {
      "step": "clickEditMenuItem",
      "result": {
        "ok": true,
        "text": "{\n  \"ok\": false,\n  \"reason\": \"edit-item-not-found\",\n  \"options\": [\n    \"Delete\",\n    \"Pin to your profile\",\n    \"Highlight on your profile\",\n    \"Add/remove from Li t\",\n    \"Mute thi  conver ation\",\n    \"Add/remove content di clo ure\",\n    \"Change who can reply\",\n    \"View po t activity\",\n    \"Embed po t\",\n    \"View po t analytic\",\n    \"View hidden replie\",\n    \"Reque t Community Note\"\n  ]\n}",
        "raw": {
          "content": [
            {
              "type": "text",
              "text": "{\n  \"ok\": false,\n  \"reason\": \"edit-item-not-found\",\n  \"options\": [\n    \"Delete\",\n    \"Pin to your profile\",\n    \"Highlight on your profile\",\n    \"Add/remove from Li t\",\n    \"Mute thi  conver ation\",\n    \"Add/remove content di clo ure\",\n    \"Change who can reply\",\n    \"View po t activity\",\n    \"Embed po t\",\n    \"View po t analytic\",\n    \"View hidden replie\",\n    \"Reque t Community Note\"\n  ]\n}"
            }
          ]
        }
      }
    },
    {
      "step": "detectEditSurface",
      "result": {
        "ok": true,
        "text": "{\n  \"ok\": true,\n  \"dialogFound\": false,\n  \"updateFound\": false,\n  \"editorFound\": true,\n  \"bodyHasEditLabel\": false,\n  \"sampleButtons\": [\n    {\n      \"text\": \"\",\n      \"aria\": \"\",\n      \"dt\": null,\n      \"disabled\": false\n    },\n    {\n      \"text\": \"\",\n      \"aria\": \"Skip to home timeline\",\n      \"dt\": null,\n      \"disabled\": false\n    },\n    {\n      \"text\": \"\",\n      \"aria\": \"Skip to trending\",\n      \"dt\": null,\n      \"disabled\": false\n    },\n    {\n      \"text\": \"\",\n      \"aria\": \"More menu item\",\n      \"dt\": \"AppTabBar_More_Menu\",\n      \"disabled\": false\n    },\n    {\n      \"text\": \"\",\n      \"aria\": \"Account menu\",\n      \"dt\": \"SideNav_AccountSwitcher_Button\",\n      \"disabled\": false\n    },\n    {\n      \"text\": \"\",\n      \"aria\": \"Back\",\n      \"dt\": \"app-bar-back\",\n      \"disabled\": false\n    },\n    {\n      \"text\": \"See new po t\",\n      \"aria\": \"New po t  are available. Pu h the period key to go to the them.\",\n      \"dt\": null,\n      \"disabled\": false\n    },\n    {\n      \"text\": \"\",\n      \"aria\": \"Grok action\",\n      \"dt\": null,\n      \"disabled\": false\n    },\n    {\n      \"text\": \"\",\n      \"aria\": \"More\",\n      \"dt\": \"caret\",\n      \"disabled\": false\n    },\n    {\n      \"text\": \"1\",\n      \"aria\": \"1 Reply. Reply\",\n      \"dt\": \"reply\",\n      \"disabled\": false\n    },\n    {\n      \"text\": \"\",\n      \"aria\": \"0 repo t . Repo t\",\n      \"dt\": \"retweet\",\n      \"disabled\": false\n    },\n    {\n      \"text\": \"\",\n      \"aria\": \"0 Like . Like\",\n      \"dt\": \"like\",\n      \"disabled\": false\n    },\n    {\n      \"text\": \"\",\n      \"aria\": \"0 Bookmark . Bookmark\",\n      \"dt\": \"bookmark\",\n      \"disabled\": false\n    },\n    {\n      \"text\": \"\",\n      \"aria\": \"Share po t\",\n      \"dt\": null,\n      \"disabled\": false\n    },\n    {\n      \"text\": \"Reply\",\n      \"aria\": \"\",\n      \"dt\": \"tweetButtonInline\",\n      \"disabled\": true\n    },\n    {\n      \"text\": \"\",\n      \"aria\": \"Grok action\",\n      \"dt\": null,\n      \"disabled\": false\n    },\n    {\n      \"text\": \"\",\n      \"aria\": \"More\",\n      \"dt\": \"caret\",\n      \"disabled\": false\n    },\n    {\n      \"text\": \"\",\n      \"aria\": \"0 Replie . Reply\",\n      \"dt\": \"reply\",\n      \"disabled\": false\n    },\n    {\n      \"text\": \"\",\n      \"aria\": \"0 repo t . Repo t\",\n      \"dt\": \"retweet\",\n      \"disabled\": false\n    },\n    {\n      \"text\": \"\",\n      \"aria\": \"0 Like . Like\",\n      \"dt\": \"like\",\n      \"disabled\": false\n    }\n  ]\n}",
        "raw": {
          "content": [
            {
              "type": "text",
              "text": "{\n  \"ok\": true,\n  \"dialogFound\": false,\n  \"updateFound\": false,\n  \"editorFound\": true,\n  \"bodyHasEditLabel\": false,\n  \"sampleButtons\": [\n    {\n      \"text\": \"\",\n      \"aria\": \"\",\n      \"dt\": null,\n      \"disabled\": false\n    },\n    {\n      \"text\": \"\",\n      \"aria\": \"Skip to home timeline\",\n      \"dt\": null,\n      \"disabled\": false\n    },\n    {\n      \"text\": \"\",\n      \"aria\": \"Skip to trending\",\n      \"dt\": null,\n      \"disabled\": false\n    },\n    {\n      \"text\": \"\",\n      \"aria\": \"More menu item\",\n      \"dt\": \"AppTabBar_More_Menu\",\n      \"disabled\": false\n    },\n    {\n      \"text\": \"\",\n      \"aria\": \"Account menu\",\n      \"dt\": \"SideNav_AccountSwitcher_Button\",\n      \"disabled\": false\n    },\n    {\n      \"text\": \"\",\n      \"aria\": \"Back\",\n      \"dt\": \"app-bar-back\",\n      \"disabled\": false\n    },\n    {\n      \"text\": \"See new po t\",\n      \"aria\": \"New po t  are available. Pu h the period key to go to the them.\",\n      \"dt\": null,\n      \"disabled\": false\n    },\n    {\n      \"text\": \"\",\n      \"aria\": \"Grok action\",\n      \"dt\": null,\n      \"disabled\": false\n    },\n    {\n      \"text\": \"\",\n      \"aria\": \"More\",\n      \"dt\": \"caret\",\n      \"disabled\": false\n    },\n    {\n      \"text\": \"1\",\n      \"aria\": \"1 Reply. Reply\",\n      \"dt\": \"reply\",\n      \"disabled\": false\n    },\n    {\n      \"text\": \"\",\n      \"aria\": \"0 repo t . Repo t\",\n      \"dt\": \"retweet\",\n      \"disabled\": false\n    },\n    {\n      \"text\": \"\",\n      \"aria\": \"0 Like . Like\",\n      \"dt\": \"like\",\n      \"disabled\": false\n    },\n    {\n      \"text\": \"\",\n      \"aria\": \"0 Bookmark . Bookmark\",\n      \"dt\": \"bookmark\",\n      \"disabled\": false\n    },\n    {\n      \"text\": \"\",\n      \"aria\": \"Share po t\",\n      \"dt\": null,\n      \"disabled\": false\n    },\n    {\n      \"text\": \"Reply\",\n      \"aria\": \"\",\n      \"dt\": \"tweetButtonInline\",\n      \"disabled\": true\n    },\n    {\n      \"text\": \"\",\n      \"aria\": \"Grok action\",\n      \"dt\": null,\n      \"disabled\": false\n    },\n    {\n      \"text\": \"\",\n      \"aria\": \"More\",\n      \"dt\": \"caret\",\n      \"disabled\": false\n    },\n    {\n      \"text\": \"\",\n      \"aria\": \"0 Replie . Reply\",\n      \"dt\": \"reply\",\n      \"disabled\": false\n    },\n    {\n      \"text\": \"\",\n      \"aria\": \"0 repo t . Repo t\",\n      \"dt\": \"retweet\",\n      \"disabled\": false\n    },\n    {\n      \"text\": \"\",\n      \"aria\": \"0 Like . Like\",\n      \"dt\": \"like\",\n      \"disabled\": false\n    }\n  ]\n}"
            }
          ]
        }
      }
    }
  ],
  "errors": [],
  "finishedAt": "2026-03-05T18:17:47.151Z"
}